coolhand/__init__.py
coolhand/client.py
coolhand/feedback_service.py
coolhand/interceptor.py
coolhand/types.py
coolhand/version.py
coolhand-0.2.0.dist-info/METADATA
coolhand-0.2.0.dist-info/WHEEL
coolhand-0.2.0.dist-info/licenses/LICENSE
coolhand-0.2.0.dist-info/RECORD
